mulmap/__init__.py
mulmap/test.py
mulmap-0.0.0.dist-info/METADATA
mulmap-0.0.0.dist-info/WHEEL
mulmap-0.0.0.dist-info/top_level.txt
mulmap-0.0.0.dist-info/RECORD
